simple_aws_rds/__init__.py
simple_aws_rds/_version.py
simple_aws_rds/api.py
simple_aws_rds/exc.py
simple_aws_rds/paths.py
simple_aws_rds/rds.py
simple_aws_rds/docs/__init__.py
simple_aws_rds/tests/__init__.py
simple_aws_rds/tests/helper.py
simple_aws_rds/tests/mock_aws.py
simple_aws_rds/vendor/__init__.py
simple_aws_rds/vendor/pytest_cov_helper.py
simple_aws_rds/vendor/waiter.py
simple_aws_rds-0.5.3.dist-info/AUTHORS.rst
simple_aws_rds-0.5.3.dist-info/LICENSE.txt
simple_aws_rds-0.5.3.dist-info/METADATA
simple_aws_rds-0.5.3.dist-info/WHEEL
simple_aws_rds-0.5.3.dist-info/top_level.txt
simple_aws_rds-0.5.3.dist-info/RECORD
